[
  {
    "rank": "1",
    "title": "The Time Machine",
    "authors": "H. G. Wells",
    "cover_url": "https://cm-fy.github.io/best-sellers-manybooks-cache/mb/covers/cover-cust-7349.jpg",
    "source_url": "https://manybooks.net/titles/wellshgetext92timem11.html",
    "manybooks_download_url": "",
    "manybooks_format": "EPUB"
  },
  {
    "rank": "2",
    "title": "The Invisible Man",
    "authors": "H. G. Wells",
    "cover_url": "https://cm-fy.github.io/best-sellers-manybooks-cache/mb/covers/cover-orig-7340.jpg",
    "source_url": "https://manybooks.net/titles/wellshgetext04nvsbl10.html",
    "manybooks_download_url": "",
    "manybooks_format": "EPUB"
  },
  {
    "rank": "3",
    "title": "Anthem",
    "authors": "Ayn Rand",
    "cover_url": "https://cm-fy.github.io/best-sellers-manybooks-cache/mb/covers/cover-cust-5832.jpg",
    "source_url": "https://manybooks.net/titles/randaynetext98anthm10.html",
    "manybooks_download_url": "",
    "manybooks_format": "EPUB"
  }
]